libyare/__init__.py
libyare/__main__.py
libyare-1.2.1.dist-info/licenses/LICENSE
libyare-1.2.1.dist-info/WHEEL
libyare-1.2.1.dist-info/METADATA
libyare-1.2.1.dist-info/RECORD
