Metadata-Version: 2.4
Name: libyare
Version: 1.2.1
Summary: LIBrary for YARE (Yet Another Regular Expression) pattern matching
Author-email: Carlo Alessandro Verre <carlo.alessandro.verre@gmail.com>
Requires-Python: >=3.6
Classifier: Programming Language :: Python :: 3
Classifier: Programming Language :: Python :: 3.6
Classifier: Development Status :: 5 - Production/Stable
Classifier: Environment :: Console
Classifier: Intended Audience :: Developers
Classifier: License :: OSI Approved :: GNU General Public License v3 or later (GPLv3+)
Classifier: Operating System :: POSIX :: Linux
License-File: LICENSE
Project-URL: Home, https://pypi.org/project/libyare
